{
  "id": "bw9-10",
  "name": "Cacturne",
  "supertype": "Pokémon",
  "subtypes": [
    "Stage 1"
  ],
  "hp": "90",
  "types": [
    "Grass"
  ],
  "evolvesFrom": "Cacnea",
  "attacks": [
    {
      "name": "Rapid-Fire Needles",
      "cost": [
        "Grass"
      ],
      "convertedEnergyCost": 1,
      "damage": "60",
      "text": "Does 30 damage to 1 of your Pokémon. (Don't apply Weakness and Resistance for Benched Pokémon.)"
    },
    {
      "name": "Payback",
      "cost": [
        "Grass",
        "Colorless"
      ],
      "convertedEnergyCost": 2,
      "damage": "30+",
      "text": "If your opponent has only 1 Prize card left, this attack does 60 more damage and discard an Energy attached to the Defending Pokémon."
    }
  ],
  "weaknesses": [
    {
      "type": "Fire",
      "value": "×2"
    }
  ],
  "resistances": [
    {
      "type": "Water",
      "value": "-20"
    }
  ],
  "retreatCost": [
    "Colorless"
  ],
  "convertedRetreatCost": 1,
  "set": {
    "id": "bw9",
    "name": "Plasma Freeze",
    "series": "Black & White",
    "printedTotal": 116,
    "total": 122,
    "legalities": {
      "unlimited": "Legal",
      "expanded": "Legal"
    },
    "ptcgoCode": "PLF",
    "releaseDate": "2013/05/08",
    "updatedAt": "2018/03/04 10:35:00",
    "images": {
      "symbol": "https://images.pokemontcg.io/bw9/symbol.png",
      "logo": "https://images.pokemontcg.io/bw9/logo.png"
    }
  },
  "number": "10",
  "artist": "Suwama Chiaki",
  "rarity": "Rare",
  "flavorText": "It becomes active at night, seeking prey that is exhausted from the day's desert heat.",
  "nationalPokedexNumbers": [
    332
  ],
  "legalities": {
    "unlimited": "Legal",
    "expanded": "Legal"
  },
  "images": {
    "small": "https://images.pokemontcg.io/bw9/10.png",
    "large": "https://images.pokemontcg.io/bw9/10_hires.png"
  }
}