{
  "id": "dp2-79",
  "name": "Cyndaquil",
  "supertype": "Pokémon",
  "subtypes": [
    "Basic"
  ],
  "level": "12",
  "hp": "60",
  "types": [
    "Fire"
  ],
  "evolvesTo": [
    "Quilava"
  ],
  "attacks": [
    {
      "name": "Tackle",
      "cost": [],
      "convertedEnergyCost": 0,
      "damage": "10",
      "text": ""
    },
    {
      "name": "Live Coal",
      "cost": [
        "Fire",
        "Colorless"
      ],
      "convertedEnergyCost": 2,
      "damage": "20",
      "text": ""
    }
  ],
  "weaknesses": [
    {
      "type": "Water",
      "value": "+10"
    }
  ],
  "retreatCost": [
    "Colorless"
  ],
  "convertedRetreatCost": 1,
  "set": {
    "id": "dp2",
    "name": "Mysterious Treasures",
    "series": "Diamond & Pearl",
    "printedTotal": 123,
    "total": 124,
    "legalities": {
      "unlimited": "Legal"
    },
    "ptcgoCode": "MT",
    "releaseDate": "2007/08/01",
    "updatedAt": "2018/03/04 10:35:00",
    "images": {
      "symbol": "https://images.pokemontcg.io/dp2/symbol.png",
      "logo": "https://images.pokemontcg.io/dp2/logo.png"
    }
  },
  "number": "79",
  "artist": "Masakazu Fukuda",
  "rarity": "Common",
  "flavorText": "It has a timid nature. If it is startled, the flames on its back burn more vigorously.",
  "nationalPokedexNumbers": [
    155
  ],
  "legalities": {
    "unlimited": "Legal"
  },
  "images": {
    "small": "https://images.pokemontcg.io/dp2/79.png",
    "large": "https://images.pokemontcg.io/dp2/79_hires.png"
  }
}