{
  "id": "ecard2-17",
  "name": "Jumpluff",
  "supertype": "Pokémon",
  "subtypes": [
    "Stage 2"
  ],
  "hp": "70",
  "types": [
    "Grass"
  ],
  "evolvesFrom": "Skiploom",
  "abilities": [
    {
      "name": "Fluff",
      "text": "During your opponent's turn, if Jumpluff would be damaged or affected by an opponent's attack and it already has at least 1 damage counter on it, flip a coin. If heads, prevent all effects of that attack (including damage).",
      "type": "Poké-Body"
    }
  ],
  "attacks": [
    {
      "name": "Cotton Punch",
      "cost": [
        "Grass"
      ],
      "convertedEnergyCost": 1,
      "damage": "30×",
      "text": "Flip 2 coins. This attack does 30 times the number of heads."
    }
  ],
  "weaknesses": [
    {
      "type": "Fire",
      "value": "×2"
    }
  ],
  "resistances": [
    {
      "type": "Water",
      "value": "-30"
    }
  ],
  "set": {
    "id": "ecard2",
    "name": "Aquapolis",
    "series": "E-Card",
    "printedTotal": 147,
    "total": 182,
    "legalities": {
      "unlimited": "Legal"
    },
    "ptcgoCode": "AQ",
    "releaseDate": "2003/01/15",
    "updatedAt": "2020/08/14 09:35:00",
    "images": {
      "symbol": "https://images.pokemontcg.io/ecard2/symbol.png",
      "logo": "https://images.pokemontcg.io/ecard2/logo.png"
    }
  },
  "number": "17",
  "artist": "Yuka Morii",
  "rarity": "Rare",
  "nationalPokedexNumbers": [
    189
  ],
  "legalities": {
    "unlimited": "Legal"
  },
  "images": {
    "small": "https://images.pokemontcg.io/ecard2/17.png",
    "large": "https://images.pokemontcg.io/ecard2/17_hires.png"
  }
}