{
  "id": "neo1-73",
  "name": "Slowpoke",
  "supertype": "Pokémon",
  "subtypes": [
    "Basic"
  ],
  "level": "20",
  "hp": "50",
  "types": [
    "Psychic"
  ],
  "evolvesTo": [
    "Slowbro",
    "Slowking"
  ],
  "attacks": [
    {
      "name": "Psyshock",
      "cost": [
        "Psychic"
      ],
      "convertedEnergyCost": 1,
      "damage": "10",
      "text": "Flip a coin. If heads, the Defending Pokémon is now Paralyzed."
    },
    {
      "name": "Water Gun",
      "cost": [
        "Water"
      ],
      "convertedEnergyCost": 1,
      "damage": "10+",
      "text": "Does 10 damage plus 10 more damage for each Water Energy attached to Slowpoke but not used to pay for this attack's Energy cost. You can't add more than 20 damage in this way."
    }
  ],
  "weaknesses": [
    {
      "type": "Psychic",
      "value": "×2"
    }
  ],
  "retreatCost": [
    "Colorless"
  ],
  "convertedRetreatCost": 1,
  "set": {
    "id": "neo1",
    "name": "Neo Genesis",
    "series": "Neo",
    "printedTotal": 111,
    "total": 111,
    "legalities": {
      "unlimited": "Legal"
    },
    "ptcgoCode": "N1",
    "releaseDate": "2000/12/16",
    "updatedAt": "2022/10/10 15:12:00",
    "images": {
      "symbol": "https://images.pokemontcg.io/neo1/symbol.png",
      "logo": "https://images.pokemontcg.io/neo1/logo.png"
    }
  },
  "number": "73",
  "artist": "Tomokazu Komiya",
  "rarity": "Common",
  "flavorText": "It lazes vacantly near water. If something bites its tail, it won't even notice for a whole day.",
  "nationalPokedexNumbers": [
    79
  ],
  "legalities": {
    "unlimited": "Legal"
  },
  "images": {
    "small": "https://images.pokemontcg.io/neo1/73.png",
    "large": "https://images.pokemontcg.io/neo1/73_hires.png"
  }
}