{
  "id": "sm12-55",
  "name": "Prinplup",
  "supertype": "Pokémon",
  "subtypes": [
    "Stage 1"
  ],
  "hp": "80",
  "types": [
    "Water"
  ],
  "evolvesFrom": "Piplup",
  "evolvesTo": [
    "Empoleon"
  ],
  "attacks": [
    {
      "name": "Water Drip",
      "cost": [
        "Water"
      ],
      "convertedEnergyCost": 1,
      "damage": "20",
      "text": ""
    },
    {
      "name": "Direct Dive",
      "cost": [
        "Water",
        "Water",
        "Water"
      ],
      "convertedEnergyCost": 3,
      "damage": "",
      "text": "Discard all Energy from this Pokémon. This attack does 100 damage to 1 of your opponent's Benched Pokémon. (Don't apply Weakness and Resistance for Benched Pokémon.)"
    }
  ],
  "weaknesses": [
    {
      "type": "Lightning",
      "value": "×2"
    }
  ],
  "retreatCost": [
    "Colorless",
    "Colorless"
  ],
  "convertedRetreatCost": 2,
  "set": {
    "id": "sm12",
    "name": "Cosmic Eclipse",
    "series": "Sun & Moon",
    "printedTotal": 236,
    "total": 272,
    "legalities": {
      "unlimited": "Legal",
      "expanded": "Legal"
    },
    "ptcgoCode": "CEC",
    "releaseDate": "2019/11/01",
    "updatedAt": "2021/09/01 05:37:00",
    "images": {
      "symbol": "https://images.pokemontcg.io/sm12/symbol.png",
      "logo": "https://images.pokemontcg.io/sm12/logo.png"
    }
  },
  "number": "55",
  "artist": "Hasuno",
  "rarity": "Uncommon",
  "flavorText": "It lives alone, away from others. Apparently, every one of them believes it is the most important.",
  "nationalPokedexNumbers": [
    394
  ],
  "legalities": {
    "unlimited": "Legal",
    "expanded": "Legal"
  },
  "images": {
    "small": "https://images.pokemontcg.io/sm12/55.png",
    "large": "https://images.pokemontcg.io/sm12/55_hires.png"
  }
}