{
  "id": "sm5-114",
  "name": "Oranguru",
  "supertype": "Pokémon",
  "subtypes": [
    "Basic"
  ],
  "hp": "120",
  "types": [
    "Colorless"
  ],
  "attacks": [
    {
      "name": "Resource Management",
      "cost": [
        "Colorless"
      ],
      "convertedEnergyCost": 1,
      "damage": "",
      "text": "Put 3 cards from your discard pile on the bottom of your deck in any order."
    },
    {
      "name": "Profound Knowledge",
      "cost": [
        "Colorless",
        "Colorless",
        "Colorless"
      ],
      "convertedEnergyCost": 3,
      "damage": "60",
      "text": "Your opponent's Active Pokémon is now Confused."
    }
  ],
  "weaknesses": [
    {
      "type": "Fighting",
      "value": "×2"
    }
  ],
  "retreatCost": [
    "Colorless",
    "Colorless"
  ],
  "convertedRetreatCost": 2,
  "set": {
    "id": "sm5",
    "name": "Ultra Prism",
    "series": "Sun & Moon",
    "printedTotal": 156,
    "total": 178,
    "legalities": {
      "unlimited": "Legal",
      "expanded": "Legal"
    },
    "ptcgoCode": "UPR",
    "releaseDate": "2018/02/02",
    "updatedAt": "2019/02/19 23:25:00",
    "images": {
      "symbol": "https://images.pokemontcg.io/sm5/symbol.png",
      "logo": "https://images.pokemontcg.io/sm5/logo.png"
    }
  },
  "number": "114",
  "artist": "Kouki Saitou",
  "rarity": "Uncommon",
  "flavorText": "Deep in the jungle, high in the lofty canopy, this Pokémon abides. On rare occasions, it shows up at the beach to match wits with Slowking.",
  "nationalPokedexNumbers": [
    765
  ],
  "legalities": {
    "unlimited": "Legal",
    "expanded": "Banned"
  },
  "images": {
    "small": "https://images.pokemontcg.io/sm5/114.png",
    "large": "https://images.pokemontcg.io/sm5/114_hires.png"
  }
}