{
  "id": "sv5-39",
  "name": "Totodile",
  "supertype": "Pokémon",
  "subtypes": [
    "Basic"
  ],
  "hp": "70",
  "types": [
    "Water"
  ],
  "evolvesTo": [
    "Croconaw"
  ],
  "attacks": [
    {
      "name": "Big Bite",
      "cost": [
        "Water"
      ],
      "convertedEnergyCost": 1,
      "damage": "10",
      "text": "During your opponent's next turn, the Defending Pokémon can't retreat."
    }
  ],
  "weaknesses": [
    {
      "type": "Lightning",
      "value": "×2"
    }
  ],
  "retreatCost": [
    "Colorless"
  ],
  "convertedRetreatCost": 1,
  "set": {
    "id": "sv5",
    "name": "Temporal Forces",
    "series": "Scarlet & Violet",
    "printedTotal": 162,
    "total": 218,
    "legalities": {
      "unlimited": "Legal",
      "standard": "Legal",
      "expanded": "Legal"
    },
    "ptcgoCode": "TEF",
    "releaseDate": "2024/03/22",
    "updatedAt": "2024/03/22 15:00:00",
    "images": {
      "symbol": "https://images.pokemontcg.io/sv5/symbol.png",
      "logo": "https://images.pokemontcg.io/sv5/logo.png"
    }
  },
  "number": "39",
  "artist": "MINAMINAMI Take",
  "rarity": "Common",
  "flavorText": "It is small but rough and tough. It won't hesitate to take a bite out of anything that moves.",
  "nationalPokedexNumbers": [
    158
  ],
  "legalities": {
    "unlimited": "Legal",
    "standard": "Legal",
    "expanded": "Legal"
  },
  "regulationMark": "H",
  "images": {
    "small": "https://images.pokemontcg.io/sv5/39.png",
    "large": "https://images.pokemontcg.io/sv5/39_hires.png"
  }
}