{
  "id": "swsh12-168",
  "name": "Regenerative Energy",
  "supertype": "Energy",
  "subtypes": [
    "Special"
  ],
  "rules": [
    "As long as this card is attached to a Pokémon, it provides Colorless Energy. Whenever you play a Pokémon from your hand to evolve the Pokémon V this card is attached to, heal 100 damage from that Pokémon."
  ],
  "set": {
    "id": "swsh12",
    "name": "Silver Tempest",
    "series": "Sword & Shield",
    "printedTotal": 195,
    "total": 215,
    "legalities": {
      "unlimited": "Legal",
      "standard": "Legal",
      "expanded": "Legal"
    },
    "ptcgoCode": "SIT",
    "releaseDate": "2022/11/11",
    "updatedAt": "2022/09/09 11:45:00",
    "images": {
      "symbol": "https://images.pokemontcg.io/swsh12/symbol.png",
      "logo": "https://images.pokemontcg.io/swsh12/logo.png"
    }
  },
  "number": "168",
  "rarity": "Uncommon",
  "legalities": {
    "unlimited": "Legal",
    "standard": "Legal",
    "expanded": "Legal"
  },
  "regulationMark": "F",
  "images": {
    "small": "https://images.pokemontcg.io/swsh12/168.png",
    "large": "https://images.pokemontcg.io/swsh12/168_hires.png"
  }
}