{
  "id": "swsh10-42",
  "name": "Dewott",
  "supertype": "Pokémon",
  "subtypes": [
    "Stage 1"
  ],
  "hp": "90",
  "types": [
    "Water"
  ],
  "evolvesFrom": "Oshawott",
  "evolvesTo": [
    "Samurott"
  ],
  "attacks": [
    {
      "name": "Razor Shell",
      "cost": [
        "Colorless"
      ],
      "convertedEnergyCost": 1,
      "damage": "20+",
      "text": "Flip a coin. If heads, this attack does 20 more damage."
    }
  ],
  "weaknesses": [
    {
      "type": "Lightning",
      "value": "×2"
    }
  ],
  "retreatCost": [
    "Colorless"
  ],
  "convertedRetreatCost": 1,
  "set": {
    "id": "swsh10",
    "name": "Astral Radiance",
    "series": "Sword & Shield",
    "printedTotal": 189,
    "total": 216,
    "legalities": {
      "unlimited": "Legal",
      "standard": "Legal",
      "expanded": "Legal"
    },
    "ptcgoCode": "ASR",
    "releaseDate": "2022/05/27",
    "updatedAt": "2022/05/27 09:45:00",
    "images": {
      "symbol": "https://images.pokemontcg.io/swsh10/symbol.png",
      "logo": "https://images.pokemontcg.io/swsh10/logo.png"
    }
  },
  "number": "42",
  "artist": "Mina Nakai",
  "rarity": "Uncommon",
  "flavorText": "Its exquisite double-scalchop technique is likely the result of daily training, and it can send even masters of the blade fleeing in defeat.",
  "nationalPokedexNumbers": [
    502
  ],
  "legalities": {
    "unlimited": "Legal",
    "standard": "Legal",
    "expanded": "Legal"
  },
  "regulationMark": "F",
  "images": {
    "small": "https://images.pokemontcg.io/swsh10/42.png",
    "large": "https://images.pokemontcg.io/swsh10/42_hires.png"
  }
}