{
  "id": "swsh2-141",
  "name": "Snorlax",
  "supertype": "Pokémon",
  "subtypes": [
    "Basic"
  ],
  "hp": "150",
  "types": [
    "Colorless"
  ],
  "attacks": [
    {
      "name": "Collect",
      "cost": [
        "Colorless"
      ],
      "convertedEnergyCost": 1,
      "damage": "",
      "text": "Draw 2 cards."
    },
    {
      "name": "Collapse",
      "cost": [
        "Colorless",
        "Colorless",
        "Colorless"
      ],
      "convertedEnergyCost": 3,
      "damage": "120",
      "text": "This Pokémon is now Asleep."
    }
  ],
  "weaknesses": [
    {
      "type": "Fighting",
      "value": "×2"
    }
  ],
  "retreatCost": [
    "Colorless",
    "Colorless",
    "Colorless",
    "Colorless"
  ],
  "convertedRetreatCost": 4,
  "set": {
    "id": "swsh2",
    "name": "Rebel Clash",
    "series": "Sword & Shield",
    "printedTotal": 192,
    "total": 209,
    "legalities": {
      "unlimited": "Legal",
      "expanded": "Legal"
    },
    "ptcgoCode": "RCL",
    "releaseDate": "2020/05/01",
    "updatedAt": "2020/09/25 10:09:00",
    "images": {
      "symbol": "https://images.pokemontcg.io/swsh2/symbol.png",
      "logo": "https://images.pokemontcg.io/swsh2/logo.png"
    }
  },
  "number": "141",
  "artist": "Eri Yamaki",
  "rarity": "Rare",
  "flavorText": "It is not satisfied unless it eats over 880 pounds of food every day. When it is done eating, it goes promptly to sleep.",
  "nationalPokedexNumbers": [
    143
  ],
  "legalities": {
    "unlimited": "Legal",
    "expanded": "Legal"
  },
  "regulationMark": "D",
  "images": {
    "small": "https://images.pokemontcg.io/swsh2/141.png",
    "large": "https://images.pokemontcg.io/swsh2/141_hires.png"
  }
}