{
  "id": "swsh10-49",
  "name": "Galarian Mr. Rime V",
  "supertype": "Pokémon",
  "subtypes": [
    "Basic",
    "V",
    "Fusion Strike"
  ],
  "hp": "210",
  "types": [
    "Water"
  ],
  "rules": [
    "V rule: When your Pokémon V is Knocked Out, your opponent takes 2 Prize cards."
  ],
  "attacks": [
    {
      "name": "Surprising Hand",
      "cost": [
        "Water"
      ],
      "convertedEnergyCost": 1,
      "damage": "",
      "text": "Search your deck for up to 3 Item cards, reveal them, and put them into your hand. Then, shuffle your deck."
    },
    {
      "name": "Customized Cane",
      "cost": [
        "Water",
        "Water",
        "Colorless"
      ],
      "convertedEnergyCost": 3,
      "damage": "90+",
      "text": "If this Pokémon has a Pokémon Tool attached, this attack does 90 more damage."
    }
  ],
  "weaknesses": [
    {
      "type": "Metal",
      "value": "×2"
    }
  ],
  "retreatCost": [
    "Colorless",
    "Colorless"
  ],
  "convertedRetreatCost": 2,
  "set": {
    "id": "swsh10",
    "name": "Astral Radiance",
    "series": "Sword & Shield",
    "printedTotal": 189,
    "total": 216,
    "legalities": {
      "unlimited": "Legal",
      "standard": "Legal",
      "expanded": "Legal"
    },
    "ptcgoCode": "ASR",
    "releaseDate": "2022/05/27",
    "updatedAt": "2022/05/27 09:45:00",
    "images": {
      "symbol": "https://images.pokemontcg.io/swsh10/symbol.png",
      "logo": "https://images.pokemontcg.io/swsh10/logo.png"
    }
  },
  "number": "49",
  "artist": "5ban Graphics",
  "rarity": "Rare Holo V",
  "nationalPokedexNumbers": [
    866
  ],
  "legalities": {
    "unlimited": "Legal",
    "standard": "Legal",
    "expanded": "Legal"
  },
  "regulationMark": "E",
  "images": {
    "small": "https://images.pokemontcg.io/swsh10/49.png",
    "large": "https://images.pokemontcg.io/swsh10/49_hires.png"
  }
}