{
  "id": "xy10-104",
  "name": "Mega Catcher",
  "supertype": "Trainer",
  "subtypes": [
    "Item"
  ],
  "rules": [
    "Switch 1 of your opponent's Benched Mega Evolution Pokémon with his or her Active Pokémon.",
    "You may play as many Item cards as you like during your turn (before your attack)."
  ],
  "set": {
    "id": "xy10",
    "name": "Fates Collide",
    "series": "XY",
    "printedTotal": 124,
    "total": 129,
    "legalities": {
      "unlimited": "Legal",
      "expanded": "Legal"
    },
    "ptcgoCode": "FCO",
    "releaseDate": "2016/05/02",
    "updatedAt": "2018/09/03 11:49:00",
    "images": {
      "symbol": "https://images.pokemontcg.io/xy10/symbol.png",
      "logo": "https://images.pokemontcg.io/xy10/logo.png"
    }
  },
  "number": "104",
  "artist": "Toyste Beach",
  "rarity": "Uncommon",
  "legalities": {
    "unlimited": "Legal",
    "expanded": "Legal"
  },
  "images": {
    "small": "https://images.pokemontcg.io/xy10/104.png",
    "large": "https://images.pokemontcg.io/xy10/104_hires.png"
  }
}