{
  "id": "bw4-85",
  "name": "Cinccino",
  "supertype": "Pokémon",
  "subtypes": [
    "Stage 1"
  ],
  "hp": "90",
  "types": [
    "Colorless"
  ],
  "evolvesFrom": "Minccino",
  "abilities": [
    {
      "name": "Smooth Coat",
      "text": "If any damage is done to this Pokémon by attacks, flip a coin. If heads, prevent that damage.",
      "type": "Ability"
    }
  ],
  "attacks": [
    {
      "name": "Echoed Voice",
      "cost": [
        "Colorless",
        "Colorless",
        "Colorless"
      ],
      "convertedEnergyCost": 3,
      "damage": "50",
      "text": "During your next turn, this Pokémon's Echoed Voice attack does 50 more damage (before applying Weakness and Resistance)."
    }
  ],
  "weaknesses": [
    {
      "type": "Fighting",
      "value": "×2"
    }
  ],
  "retreatCost": [
    "Colorless"
  ],
  "convertedRetreatCost": 1,
  "set": {
    "id": "bw4",
    "name": "Next Destinies",
    "series": "Black & White",
    "printedTotal": 99,
    "total": 103,
    "legalities": {
      "unlimited": "Legal",
      "expanded": "Legal"
    },
    "ptcgoCode": "NXD",
    "releaseDate": "2012/02/08",
    "updatedAt": "2019/01/28 16:44:00",
    "images": {
      "symbol": "https://images.pokemontcg.io/bw4/symbol.png",
      "logo": "https://images.pokemontcg.io/bw4/logo.png"
    }
  },
  "number": "85",
  "artist": "Kanako Eo",
  "rarity": "Rare Holo",
  "flavorText": "Their white fur is coated in a special oil that makes it easy for them to deflect attacks.",
  "nationalPokedexNumbers": [
    573
  ],
  "legalities": {
    "unlimited": "Legal",
    "expanded": "Legal"
  },
  "images": {
    "small": "https://images.pokemontcg.io/bw4/85.png",
    "large": "https://images.pokemontcg.io/bw4/85_hires.png"
  }
}