{
  "id": "ex15-74",
  "name": "Holon Legacy",
  "supertype": "Trainer",
  "subtypes": [
    "Stadium"
  ],
  "rules": [
    "This card stays in play when you play it. Discard this card if another Stadium card comes into play. If another card with the same name is in play, you can't play this card.",
    "Each Pokémon in play that has δ on its card (both yours and your opponent's) has no Weakness and can't use any Poké-Powers."
  ],
  "set": {
    "id": "ex15",
    "name": "Dragon Frontiers",
    "series": "EX",
    "printedTotal": 101,
    "total": 101,
    "legalities": {
      "unlimited": "Legal"
    },
    "ptcgoCode": "DF",
    "releaseDate": "2006/11/01",
    "updatedAt": "2020/08/14 09:35:00",
    "images": {
      "symbol": "https://images.pokemontcg.io/ex15/symbol.png",
      "logo": "https://images.pokemontcg.io/ex15/logo.png"
    }
  },
  "number": "74",
  "artist": "Shizurow",
  "rarity": "Uncommon",
  "legalities": {
    "unlimited": "Legal"
  },
  "images": {
    "small": "https://images.pokemontcg.io/ex15/74.png",
    "large": "https://images.pokemontcg.io/ex15/74_hires.png"
  }
}