{
  "id": "ex4-8",
  "name": "Team Magma's Claydol",
  "supertype": "Pokémon",
  "subtypes": [
    "Stage 1"
  ],
  "hp": "80",
  "types": [
    "Psychic",
    "Darkness"
  ],
  "evolvesFrom": "Team Magma's Baltoy",
  "rules": [
    "This Pokémon is both Psychic Darkness type."
  ],
  "abilities": [
    {
      "name": "Magma Switch",
      "text": "Once during your turn (before your attack), you may move an Energy card attached to your Pokémon with Team Magma in its name to another of your Pokémon. This power can't be used if Team Magma's Claydol is affected by a Special Condition.",
      "type": "Poké-Power"
    }
  ],
  "attacks": [
    {
      "name": "Dark Hand",
      "cost": [
        "Psychic",
        "Colorless",
        "Colorless"
      ],
      "convertedEnergyCost": 3,
      "damage": "40+",
      "text": "If you have more cards in your hand than your opponent, this attack does 40 damage plus 20 more damage."
    }
  ],
  "weaknesses": [
    {
      "type": "Psychic",
      "value": "×2"
    }
  ],
  "retreatCost": [
    "Colorless",
    "Colorless"
  ],
  "convertedRetreatCost": 2,
  "set": {
    "id": "ex4",
    "name": "Team Magma vs Team Aqua",
    "series": "EX",
    "printedTotal": 95,
    "total": 97,
    "legalities": {
      "unlimited": "Legal"
    },
    "ptcgoCode": "MA",
    "releaseDate": "2004/03/01",
    "updatedAt": "2019/01/28 16:44:00",
    "images": {
      "symbol": "https://images.pokemontcg.io/ex4/symbol.png",
      "logo": "https://images.pokemontcg.io/ex4/logo.png"
    }
  },
  "number": "8",
  "artist": "Zu-Ka",
  "rarity": "Rare Holo",
  "nationalPokedexNumbers": [
    344
  ],
  "legalities": {
    "unlimited": "Legal"
  },
  "images": {
    "small": "https://images.pokemontcg.io/ex4/8.png",
    "large": "https://images.pokemontcg.io/ex4/8_hires.png"
  }
}