{
  "id": "pl4-14",
  "name": "Bronzong",
  "supertype": "Pokémon",
  "subtypes": [
    "Stage 1"
  ],
  "level": "49",
  "hp": "90",
  "types": [
    "Metal"
  ],
  "evolvesFrom": "Bronzor",
  "attacks": [
    {
      "name": "Oracle Arrow",
      "cost": [
        "Metal",
        "Colorless"
      ],
      "convertedEnergyCost": 2,
      "damage": "",
      "text": "Choose 1 of your opponent's Pokémon that has any damage counters on it. This attack does 40 damage to that Pokémon. (Don't apply Weakness and Resistance for Benched Pokémon.)"
    },
    {
      "name": "Antigravity",
      "cost": [
        "Metal",
        "Colorless",
        "Colorless"
      ],
      "convertedEnergyCost": 3,
      "damage": "60",
      "text": "The Retreat Cost for Bronzong is 0 until the end of your next turn."
    }
  ],
  "weaknesses": [
    {
      "type": "Fire",
      "value": "+20"
    }
  ],
  "resistances": [
    {
      "type": "Psychic",
      "value": "-20"
    }
  ],
  "retreatCost": [
    "Colorless",
    "Colorless",
    "Colorless"
  ],
  "convertedRetreatCost": 3,
  "set": {
    "id": "pl4",
    "name": "Arceus",
    "series": "Platinum",
    "printedTotal": 99,
    "total": 111,
    "legalities": {
      "unlimited": "Legal"
    },
    "ptcgoCode": "AR",
    "releaseDate": "2009/11/04",
    "updatedAt": "2021/07/15 11:30:00",
    "images": {
      "symbol": "https://images.pokemontcg.io/pl4/symbol.png",
      "logo": "https://images.pokemontcg.io/pl4/logo.png"
    }
  },
  "number": "14",
  "artist": "Atsuko Nishida",
  "rarity": "Rare",
  "flavorText": "It brought rains by opening portals to another world. It was revered as a bringer of plentiful harvests.",
  "nationalPokedexNumbers": [
    437
  ],
  "legalities": {
    "unlimited": "Legal"
  },
  "images": {
    "small": "https://images.pokemontcg.io/pl4/14.png",
    "large": "https://images.pokemontcg.io/pl4/14_hires.png"
  }
}