{
  "id": "sm10-28",
  "name": "Torracat",
  "supertype": "Pokémon",
  "subtypes": [
    "Stage 1"
  ],
  "hp": "80",
  "types": [
    "Fire"
  ],
  "evolvesFrom": "Litten",
  "evolvesTo": [
    "Incineroar"
  ],
  "attacks": [
    {
      "name": "Fire Fang",
      "cost": [
        "Fire"
      ],
      "convertedEnergyCost": 1,
      "damage": "20",
      "text": "Your opponent's Active Pokémon is now Burned."
    }
  ],
  "weaknesses": [
    {
      "type": "Water",
      "value": "×2"
    }
  ],
  "retreatCost": [
    "Colorless"
  ],
  "convertedRetreatCost": 1,
  "set": {
    "id": "sm10",
    "name": "Unbroken Bonds",
    "series": "Sun & Moon",
    "printedTotal": 214,
    "total": 234,
    "legalities": {
      "unlimited": "Legal",
      "expanded": "Legal"
    },
    "ptcgoCode": "UNB",
    "releaseDate": "2019/05/03",
    "updatedAt": "2021/09/01 05:37:00",
    "images": {
      "symbol": "https://images.pokemontcg.io/sm10/symbol.png",
      "logo": "https://images.pokemontcg.io/sm10/logo.png"
    }
  },
  "number": "28",
  "artist": "tetsuya koizumi",
  "rarity": "Uncommon",
  "flavorText": "It can act spoiled if it grows close to its Trainer. A powerful Pokémon, its sharp claws can leave its Trainer's whole body covered in scratches.",
  "nationalPokedexNumbers": [
    726
  ],
  "legalities": {
    "unlimited": "Legal",
    "expanded": "Legal"
  },
  "images": {
    "small": "https://images.pokemontcg.io/sm10/28.png",
    "large": "https://images.pokemontcg.io/sm10/28_hires.png"
  }
}