{
  "id": "sm5-56",
  "name": "Croagunk",
  "supertype": "Pokémon",
  "subtypes": [
    "Basic"
  ],
  "hp": "60",
  "types": [
    "Psychic"
  ],
  "evolvesTo": [
    "Toxicroak"
  ],
  "attacks": [
    {
      "name": "Swagger",
      "cost": [
        "Psychic"
      ],
      "convertedEnergyCost": 1,
      "damage": "10",
      "text": "Flip a coin. If heads, discard an Energy from your opponent's Active Pokémon."
    }
  ],
  "weaknesses": [
    {
      "type": "Psychic",
      "value": "×2"
    }
  ],
  "retreatCost": [
    "Colorless"
  ],
  "convertedRetreatCost": 1,
  "set": {
    "id": "sm5",
    "name": "Ultra Prism",
    "series": "Sun & Moon",
    "printedTotal": 156,
    "total": 178,
    "legalities": {
      "unlimited": "Legal",
      "expanded": "Legal"
    },
    "ptcgoCode": "UPR",
    "releaseDate": "2018/02/02",
    "updatedAt": "2019/02/19 23:25:00",
    "images": {
      "symbol": "https://images.pokemontcg.io/sm5/symbol.png",
      "logo": "https://images.pokemontcg.io/sm5/logo.png"
    }
  },
  "number": "56",
  "artist": "SATOSHI NAKAI",
  "rarity": "Common",
  "flavorText": "Inflating its poison sacs, it fills the area with an odd sound and hits flinching opponents with a poison jab.",
  "nationalPokedexNumbers": [
    453
  ],
  "legalities": {
    "unlimited": "Legal",
    "expanded": "Legal"
  },
  "images": {
    "small": "https://images.pokemontcg.io/sm5/56.png",
    "large": "https://images.pokemontcg.io/sm5/56_hires.png"
  }
}