{
  "id": "sm9-9",
  "name": "Pinsir",
  "supertype": "Pokémon",
  "subtypes": [
    "Basic"
  ],
  "hp": "120",
  "types": [
    "Grass"
  ],
  "attacks": [
    {
      "name": "Grip and Squeeze",
      "cost": [
        "Colorless",
        "Colorless"
      ],
      "convertedEnergyCost": 2,
      "damage": "30",
      "text": "The Defending Pokémon can't retreat during your opponent's next turn."
    },
    {
      "name": "Guillotine Hug",
      "cost": [
        "Grass",
        "Colorless",
        "Colorless"
      ],
      "convertedEnergyCost": 3,
      "damage": "",
      "text": "Flip 2 coins. If both of them are heads, your opponent's Active Pokémon is Knocked Out."
    }
  ],
  "weaknesses": [
    {
      "type": "Fire",
      "value": "×2"
    }
  ],
  "retreatCost": [
    "Colorless",
    "Colorless",
    "Colorless"
  ],
  "convertedRetreatCost": 3,
  "set": {
    "id": "sm9",
    "name": "Team Up",
    "series": "Sun & Moon",
    "printedTotal": 181,
    "total": 198,
    "legalities": {
      "unlimited": "Legal",
      "expanded": "Legal"
    },
    "ptcgoCode": "TEU",
    "releaseDate": "2019/02/01",
    "updatedAt": "2021/09/01 05:37:00",
    "images": {
      "symbol": "https://images.pokemontcg.io/sm9/symbol.png",
      "logo": "https://images.pokemontcg.io/sm9/logo.png"
    }
  },
  "number": "9",
  "artist": "Eri Yamaki",
  "rarity": "Rare",
  "flavorText": "It gets into territorial disputes with Vikavolt. For some reason, it apparently gets along well with Heracross in Alola.",
  "nationalPokedexNumbers": [
    127
  ],
  "legalities": {
    "unlimited": "Legal",
    "expanded": "Legal"
  },
  "images": {
    "small": "https://images.pokemontcg.io/sm9/9.png",
    "large": "https://images.pokemontcg.io/sm9/9_hires.png"
  }
}