{
  "id": "sv9-100",
  "name": "Lokix",
  "supertype": "Pokémon",
  "subtypes": [
    "Stage 1"
  ],
  "hp": "120",
  "types": [
    "Darkness"
  ],
  "evolvesFrom": "Nymble",
  "attacks": [
    {
      "name": "Low Sweep",
      "cost": [
        "Darkness"
      ],
      "convertedEnergyCost": 1,
      "damage": "60",
      "text": ""
    }
  ],
  "weaknesses": [
    {
      "type": "Grass",
      "value": "×2"
    }
  ],
  "retreatCost": [
    "Colorless"
  ],
  "convertedRetreatCost": 1,
  "set": {
    "id": "sv9",
    "name": "Journey Together",
    "series": "Scarlet & Violet",
    "printedTotal": 159,
    "total": 190,
    "legalities": {
      "unlimited": "Legal",
      "standard": "Legal",
      "expanded": "Legal"
    },
    "ptcgoCode": "JTG",
    "releaseDate": "2025/03/28",
    "updatedAt": "2025/03/27 16:00:00",
    "images": {
      "symbol": "https://images.pokemontcg.io/sv9/symbol.png",
      "logo": "https://images.pokemontcg.io/sv9/logo.png"
    }
  },
  "number": "100",
  "artist": "AKIRA EGAWA",
  "rarity": "Uncommon",
  "flavorText": "It uses its normally folded third set of legs when in Showdown Mode. This places a huge burden on its body, so it can't stay in this mode for long.",
  "nationalPokedexNumbers": [
    920
  ],
  "legalities": {
    "unlimited": "Legal",
    "standard": "Legal",
    "expanded": "Legal"
  },
  "regulationMark": "H",
  "images": {
    "small": "https://images.pokemontcg.io/sv9/100.png",
    "large": "https://images.pokemontcg.io/sv9/100_hires.png"
  }
}