{
  "id": "swsh5-178",
  "name": "Octillery",
  "supertype": "Pokémon",
  "subtypes": [
    "Stage 1",
    "Rapid Strike"
  ],
  "hp": "110",
  "types": [
    "Water"
  ],
  "evolvesFrom": "Remoraid",
  "abilities": [
    {
      "name": "Rapid Strike Search",
      "text": "Once during your turn, you may search your deck for a Rapid Strike card, reveal it, and put it into your hand. Then, shuffle your deck. You can't use more than 1 Rapid Strike Search Ability each turn.",
      "type": "Ability"
    }
  ],
  "attacks": [
    {
      "name": "Waterfall",
      "cost": [
        "Water",
        "Colorless",
        "Colorless"
      ],
      "convertedEnergyCost": 3,
      "damage": "50",
      "text": ""
    }
  ],
  "weaknesses": [
    {
      "type": "Lightning",
      "value": "×2"
    }
  ],
  "retreatCost": [
    "Colorless",
    "Colorless"
  ],
  "convertedRetreatCost": 2,
  "set": {
    "id": "swsh5",
    "name": "Battle Styles",
    "series": "Sword & Shield",
    "printedTotal": 163,
    "total": 183,
    "legalities": {
      "unlimited": "Legal",
      "standard": "Legal",
      "expanded": "Legal"
    },
    "ptcgoCode": "BST",
    "releaseDate": "2021/03/19",
    "updatedAt": "2021/03/19 15:12:00",
    "images": {
      "symbol": "https://images.pokemontcg.io/swsh5/symbol.png",
      "logo": "https://images.pokemontcg.io/swsh5/logo.png"
    }
  },
  "number": "178",
  "artist": "PLANETA Mochizuki",
  "rarity": "Rare Secret",
  "flavorText": "It traps enemies with its suction-cupped tentacles, then smashes them with its rock-hard head.",
  "nationalPokedexNumbers": [
    224
  ],
  "legalities": {
    "unlimited": "Legal",
    "standard": "Legal",
    "expanded": "Legal"
  },
  "regulationMark": "E",
  "images": {
    "small": "https://images.pokemontcg.io/swsh5/178.png",
    "large": "https://images.pokemontcg.io/swsh5/178_hires.png"
  }
}