{
  "id": "swsh11-113",
  "name": "Ariados",
  "supertype": "Pokémon",
  "subtypes": [
    "Stage 1"
  ],
  "hp": "90",
  "types": [
    "Darkness"
  ],
  "evolvesFrom": "Spinarak",
  "attacks": [
    {
      "name": "String Bind",
      "cost": [
        "Darkness"
      ],
      "convertedEnergyCost": 1,
      "damage": "10+",
      "text": "This attack does 30 more damage for each Colorless in your opponent's Active Pokémon's Retreat Cost."
    },
    {
      "name": "Venomous Fang",
      "cost": [
        "Darkness",
        "Colorless",
        "Colorless"
      ],
      "convertedEnergyCost": 3,
      "damage": "80",
      "text": "Your opponent's Active Pokémon is now Poisoned."
    }
  ],
  "weaknesses": [
    {
      "type": "Fighting",
      "value": "×2"
    }
  ],
  "retreatCost": [
    "Colorless"
  ],
  "convertedRetreatCost": 1,
  "set": {
    "id": "swsh11",
    "name": "Lost Origin",
    "series": "Sword & Shield",
    "printedTotal": 196,
    "total": 217,
    "legalities": {
      "unlimited": "Legal",
      "standard": "Legal",
      "expanded": "Legal"
    },
    "ptcgoCode": "LOR",
    "releaseDate": "2022/09/09",
    "updatedAt": "2022/09/09 13:45:00",
    "images": {
      "symbol": "https://images.pokemontcg.io/swsh11/symbol.png",
      "logo": "https://images.pokemontcg.io/swsh11/logo.png"
    }
  },
  "number": "113",
  "artist": "Shinji Kanda",
  "rarity": "Rare",
  "flavorText": "It spews threads from its mouth to catch its prey. When night falls, it leaves its web to go hunt aggressively.",
  "nationalPokedexNumbers": [
    168
  ],
  "legalities": {
    "unlimited": "Legal",
    "standard": "Legal",
    "expanded": "Legal"
  },
  "regulationMark": "F",
  "images": {
    "small": "https://images.pokemontcg.io/swsh11/113.png",
    "large": "https://images.pokemontcg.io/swsh11/113_hires.png"
  }
}