{
  "id": "xy12-34",
  "name": "Gyarados",
  "supertype": "Pokémon",
  "subtypes": [
    "Stage 1"
  ],
  "level": "41",
  "hp": "130",
  "types": [
    "Water"
  ],
  "evolvesFrom": "Magikarp",
  "attacks": [
    {
      "name": "Bubble Beam",
      "cost": [
        "Water",
        "Water",
        "Water"
      ],
      "convertedEnergyCost": 3,
      "damage": "50",
      "text": "Flip a coin. If heads, your opponent's Active Pokémon is now Paralyzed."
    },
    {
      "name": "Dragon Rage",
      "cost": [
        "Water",
        "Water",
        "Water",
        "Water"
      ],
      "convertedEnergyCost": 4,
      "damage": "180",
      "text": "Flip 2 coins. If either of them is tails, this attack does nothing."
    }
  ],
  "weaknesses": [
    {
      "type": "Lightning",
      "value": "×2"
    }
  ],
  "retreatCost": [
    "Colorless",
    "Colorless",
    "Colorless"
  ],
  "convertedRetreatCost": 3,
  "set": {
    "id": "xy12",
    "name": "Evolutions",
    "series": "XY",
    "printedTotal": 108,
    "total": 113,
    "legalities": {
      "unlimited": "Legal",
      "expanded": "Legal"
    },
    "ptcgoCode": "EVO",
    "releaseDate": "2016/11/02",
    "updatedAt": "2020/09/25 10:09:00",
    "images": {
      "symbol": "https://images.pokemontcg.io/xy12/symbol.png",
      "logo": "https://images.pokemontcg.io/xy12/logo.png"
    }
  },
  "number": "34",
  "artist": "Mitsuhiro Arita",
  "rarity": "Rare Holo",
  "flavorText": "It has an extremely aggressive nature. The Hyper Beam it shoots from its mouth totally incinerates all targets.",
  "nationalPokedexNumbers": [
    130
  ],
  "legalities": {
    "unlimited": "Legal",
    "expanded": "Legal"
  },
  "images": {
    "small": "https://images.pokemontcg.io/xy12/34.png",
    "large": "https://images.pokemontcg.io/xy12/34_hires.png"
  }
}